tags_append_library/__init__.py
tags_append_library/tags_append_library.py
tags_append_library-0.2.dist-info/METADATA
tags_append_library-0.2.dist-info/WHEEL
tags_append_library-0.2.dist-info/top_level.txt
tags_append_library-0.2.dist-info/RECORD
