Metadata-Version: 2.1
Name: tags_append_library
Version: 0.2
Summary: A library to append viral tags to posts automatically
